{
  "total_records": 1196671,
  "splits": {
    "train": 836957,
    "val": 177840,
    "test": 181874
  },
  "label_distribution": {
    "train": {
      "safe": 382736,
      "unsafe": 454221
    },
    "val": {
      "safe": 81275,
      "unsafe": 96565
    },
    "test": {
      "safe": 83140,
      "unsafe": 98734
    }
  },
  "dialect_distribution": {
    "train": {
      "aboriginal_english": 21201,
      "acrolectal_fiji_english": 16245,
      "appalachian_english": 16324,
      "australian_english": 16141,
      "australian_vernacular_english": 11687,
      "bahamian_english": 9392,
      "black_south_african_english": 9332,
      "cameroon_english": 14223,
      "cape_flats_english": 14198,
      "channel_islands_english": 14214,
      "chicano_english": 18836,
      "colloquial_american_english": 16332,
      "colloquial_singapore_english_singlish": 16303,
      "earlier_african_american_vernacular_english": 16142,
      "east_anglian_english": 21104,
      "english_dialects_in_the_north_of_england": 21143,
      "english_dialects_in_the_southeast_of_england": 20052,
      "english_dialects_in_the_southwest_of_england": 18315,
      "falkland_islands_english": 16223,
      "ghanaian_english": 16314,
      "hong_kong_english": 16621,
      "indian_english": 21534,
      "indian_south_african_english": 21343,
      "irish_english": 21522,
      "jamaican_english": 18259,
      "kenyan_english": 16700,
      "liberian_settler_english": 16607,
      "malaysian_english": 16609,
      "maltese_english": 21457,
      "manx_english": 21472,
      "new_zealand_english": 21332,
      "newfoundland_english": 17407,
      "nigerian_english": 16620,
      "orkney_and_shetland_english": 16580,
      "ozark_english": 16392,
      "pakistani_english": 21460,
      "philippine_english": 19293,
      "pure_fiji_english_basilectal_fijie": 16629,
      "rural_african_american_vernacular_english": 16521,
      "scottish_english": 16669,
      "southeast_american_enclave_dialects": 16608,
      "sri_lankan_english": 16645,
      "st_helena_english": 21533,
      "tanzanian_english": 20675,
      "tristan_da_cunha_english": 16619,
      "ugandan_english": 16344,
      "urban_african_american_vernacular_english": 16460,
      "welsh_english": 15645,
      "white_south_african_english": 840,
      "white_zimbabwean_english": 840
    },
    "val": {
      "aboriginal_english": 4491,
      "acrolectal_fiji_english": 3428,
      "appalachian_english": 3461,
      "australian_english": 3426,
      "australian_vernacular_english": 2462,
      "bahamian_english": 1988,
      "black_south_african_english": 1991,
      "cameroon_english": 3042,
      "cape_flats_english": 3053,
      "channel_islands_english": 3053,
      "chicano_english": 4005,
      "colloquial_american_english": 3477,
      "colloquial_singapore_english_singlish": 3475,
      "earlier_african_american_vernacular_english": 3423,
      "east_anglian_english": 4493,
      "english_dialects_in_the_north_of_england": 4519,
      "english_dialects_in_the_southeast_of_england": 4298,
      "english_dialects_in_the_southwest_of_england": 3908,
      "falkland_islands_english": 3437,
      "ghanaian_english": 3460,
      "hong_kong_english": 3511,
      "indian_english": 4594,
      "indian_south_african_english": 4566,
      "irish_english": 4584,
      "jamaican_english": 3851,
      "kenyan_english": 3540,
      "liberian_settler_english": 3527,
      "malaysian_english": 3525,
      "maltese_english": 4574,
      "manx_english": 4575,
      "new_zealand_english": 4538,
      "newfoundland_english": 3713,
      "nigerian_english": 3510,
      "orkney_and_shetland_english": 3510,
      "ozark_english": 3489,
      "pakistani_english": 4573,
      "philippine_english": 4083,
      "pure_fiji_english_basilectal_fijie": 3527,
      "rural_african_american_vernacular_english": 3483,
      "scottish_english": 3525,
      "southeast_american_enclave_dialects": 3511,
      "sri_lankan_english": 3541,
      "st_helena_english": 4589,
      "tanzanian_english": 4389,
      "tristan_da_cunha_english": 3495,
      "ugandan_english": 3455,
      "urban_african_american_vernacular_english": 3481,
      "welsh_english": 3319,
      "white_south_african_english": 186,
      "white_zimbabwean_english": 186
    },
    "test": {
      "aboriginal_english": 4600,
      "acrolectal_fiji_english": 3535,
      "appalachian_english": 3552,
      "australian_english": 3525,
      "australian_vernacular_english": 2533,
      "bahamian_english": 2044,
      "black_south_african_english": 2031,
      "cameroon_english": 3083,
      "cape_flats_english": 3065,
      "channel_islands_english": 3078,
      "chicano_english": 4092,
      "colloquial_american_english": 3548,
      "colloquial_singapore_english_singlish": 3538,
      "earlier_african_american_vernacular_english": 3508,
      "east_anglian_english": 4597,
      "english_dialects_in_the_north_of_england": 4608,
      "english_dialects_in_the_southeast_of_england": 4363,
      "english_dialects_in_the_southwest_of_england": 3971,
      "falkland_islands_english": 3534,
      "ghanaian_english": 3550,
      "hong_kong_english": 3614,
      "indian_english": 4670,
      "indian_south_african_english": 4640,
      "irish_english": 4668,
      "jamaican_english": 3944,
      "kenyan_english": 3634,
      "liberian_settler_english": 3595,
      "malaysian_english": 3604,
      "maltese_english": 4666,
      "manx_english": 4664,
      "new_zealand_english": 4641,
      "newfoundland_english": 3798,
      "nigerian_english": 3623,
      "orkney_and_shetland_english": 3616,
      "ozark_english": 3574,
      "pakistani_english": 4658,
      "philippine_english": 4150,
      "pure_fiji_english_basilectal_fijie": 3612,
      "rural_african_american_vernacular_english": 3594,
      "scottish_english": 3622,
      "southeast_american_enclave_dialects": 3606,
      "sri_lankan_english": 3618,
      "st_helena_english": 4660,
      "tanzanian_english": 4492,
      "tristan_da_cunha_english": 3624,
      "ugandan_english": 3560,
      "urban_african_american_vernacular_english": 3596,
      "welsh_english": 3408,
      "white_south_african_english": 184,
      "white_zimbabwean_english": 184
    }
  },
  "dataset_distribution": {
    "train": {
      "Salad_Bench": 154588,
      "Simple_Safety_Tests": 25553,
      "Toxic_Text": 44580,
      "Toxicity_Jigsaw": 41920,
      "advbench": 78792,
      "bipia": 23203,
      "cyberseceval": 82533,
      "do_not_answer": 49601,
      "forbiddent_questions": 66696,
      "harmBench": 46685,
      "injecagent": 49996,
      "jailbreakbench": 48125,
      "llmseceval": 37289,
      "securityeval": 38630,
      "sorry_bench": 48766
    },
    "val": {
      "Salad_Bench": 34129,
      "Simple_Safety_Tests": 4974,
      "Toxic_Text": 9278,
      "Toxicity_Jigsaw": 8478,
      "advbench": 17904,
      "bipia": 5060,
      "cyberseceval": 17032,
      "do_not_answer": 10588,
      "forbiddent_questions": 14202,
      "harmBench": 10166,
      "injecagent": 10697,
      "jailbreakbench": 10564,
      "llmseceval": 7867,
      "securityeval": 6468,
      "sorry_bench": 10433
    },
    "test": {
      "Salad_Bench": 34139,
      "Simple_Safety_Tests": 5726,
      "Toxic_Text": 9886,
      "Toxicity_Jigsaw": 9379,
      "advbench": 15443,
      "bipia": 4704,
      "cyberseceval": 18887,
      "do_not_answer": 10675,
      "forbiddent_questions": 16010,
      "harmBench": 9884,
      "injecagent": 10722,
      "jailbreakbench": 10202,
      "llmseceval": 8138,
      "securityeval": 7652,
      "sorry_bench": 10427
    }
  },
  "text_type_distribution": {
    "train": {
      "basic_transform": 77410,
      "coi_transform": 83341,
      "counterharm_basic": 68336,
      "counterharm_coi": 73349,
      "counterharm_original": 78577,
      "counterharm_transformed": 75381,
      "mv_counterharm": 43554,
      "mv_counterharm_trans": 43539,
      "mv_transform": 118294,
      "original": 89371,
      "transformed": 85805
    },
    "val": {
      "basic_transform": 16312,
      "coi_transform": 17655,
      "counterharm_basic": 14394,
      "counterharm_coi": 15542,
      "counterharm_original": 16556,
      "counterharm_transformed": 15830,
      "mv_counterharm": 9479,
      "mv_counterharm_trans": 9474,
      "mv_transform": 25755,
      "original": 18831,
      "transformed": 18012
    },
    "test": {
      "basic_transform": 17076,
      "coi_transform": 18197,
      "counterharm_basic": 15069,
      "counterharm_coi": 16028,
      "counterharm_original": 17017,
      "counterharm_transformed": 16326,
      "mv_counterharm": 9352,
      "mv_counterharm_trans": 9348,
      "mv_transform": 25514,
      "original": 19359,
      "transformed": 18588
    }
  }
}